hyrax/__init__.py
hyrax/_version.py
hyrax/config_utils.py
hyrax/download.py
hyrax/download_stats.py
hyrax/gpu_monitor.py
hyrax/hyrax.py
hyrax/hyrax_default_config.toml
hyrax/model_exporters.py
hyrax/plugin_utils.py
hyrax/prepare.py
hyrax/pytorch_ignite.py
hyrax/rebuild_manifest.py
hyrax/3d_viz/.gitattributes
hyrax/3d_viz/fits.js
hyrax/3d_viz/image-viewer.js
hyrax/3d_viz/index.html
hyrax/3d_viz/plotly_3d.py
hyrax/3d_viz/readme.md
hyrax/3d_viz/save_umap_to_json.py
hyrax/3d_viz/script.js
hyrax/3d_viz/start_3d_viz_server.py
hyrax/3d_viz/styles.css
hyrax/data_sets/__init__.py
hyrax/data_sets/data_provider.py
hyrax/data_sets/data_set_registry.py
hyrax/data_sets/downloaded_lsst_dataset.py
hyrax/data_sets/fits_image_dataset.py
hyrax/data_sets/hsc_data_set.py
hyrax/data_sets/hyrax_cifar_dataset.py
hyrax/data_sets/hyrax_csv_dataset.py
hyrax/data_sets/inference_dataset.py
hyrax/data_sets/lsst_dataset.py
hyrax/data_sets/tensor_cache_mixin.py
hyrax/data_sets/random/__init__.py
hyrax/data_sets/random/hyrax_random_dataset.py
hyrax/downloadCutout/LINCC_README.md
hyrax/downloadCutout/README.md
hyrax/downloadCutout/__init__.py
hyrax/downloadCutout/downloadCutout.py
hyrax/models/__init__.py
hyrax/models/hsc_autoencoder.py
hyrax/models/hsc_dcae.py
hyrax/models/hyrax_autoencoder.py
hyrax/models/hyrax_autoencoderv2.py
hyrax/models/hyrax_cnn.py
hyrax/models/hyrax_loopback.py
hyrax/models/image_dcae.py
hyrax/models/model_registry.py
hyrax/models/simclr.py
hyrax/vector_dbs/__init__.py
hyrax/vector_dbs/chromadb_impl.py
hyrax/vector_dbs/qdrantdb_impl.py
hyrax/vector_dbs/vector_db_factory.py
hyrax/vector_dbs/vector_db_interface.py
hyrax/verbs/__init__.py
hyrax/verbs/database_connection.py
hyrax/verbs/engine.py
hyrax/verbs/infer.py
hyrax/verbs/lookup.py
hyrax/verbs/model.py
hyrax/verbs/save_to_database.py
hyrax/verbs/search.py
hyrax/verbs/to_onnx.py
hyrax/verbs/train.py
hyrax/verbs/umap.py
hyrax/verbs/verb_registry.py
hyrax/verbs/visualize.py
hyrax-0.6.10.dist-info/licenses/LICENSE
hyrax_cli/main.py
hyrax-0.6.10.dist-info/METADATA
hyrax-0.6.10.dist-info/WHEEL
hyrax-0.6.10.dist-info/entry_points.txt
hyrax-0.6.10.dist-info/top_level.txt
hyrax-0.6.10.dist-info/RECORD
