Metadata-Version: 2.4
Name: hyrax
Version: 0.6.10
Author-email: LINCC Frameworks <mtauraso@uw.edu>
License-Expression: MIT
Project-URL: Source Code, https://github.com/lincc-frameworks/hyrax
Classifier: Development Status :: 4 - Beta
Classifier: Intended Audience :: Developers
Classifier: Intended Audience :: Science/Research
Classifier: Operating System :: OS Independent
Classifier: Programming Language :: Python
Requires-Python: >=3.10
License-File: LICENSE
Requires-Dist: astropy
Requires-Dist: pytorch-ignite<=0.5.3
Requires-Dist: more-itertools
Requires-Dist: toml
Requires-Dist: tomlkit
Requires-Dist: torch
Requires-Dist: torchvision
Requires-Dist: tensorboardX
Requires-Dist: tensorboard
Requires-Dist: schwimmbad
Requires-Dist: chromadb>1.0
Requires-Dist: holoviews
Requires-Dist: bokeh
Requires-Dist: jupyter_bokeh
Requires-Dist: datashader
Requires-Dist: pandas
Requires-Dist: numpy
Requires-Dist: scipy
Requires-Dist: cython
Requires-Dist: mlflow
Requires-Dist: pynvml
Requires-Dist: umap-learn
Requires-Dist: pooch
Requires-Dist: onnx
Requires-Dist: onnxruntime
Requires-Dist: onnxscript
Requires-Dist: plotly
Requires-Dist: psutil
Requires-Dist: tqdm
Requires-Dist: qdrant-client
Requires-Dist: colorama
Requires-Dist: numba==0.63.1
Provides-Extra: examples
Provides-Extra: dev
Requires-Dist: asv[virtualenv]==0.6.5; extra == "dev"
Requires-Dist: jupyter; extra == "dev"
Requires-Dist: matplotlib; extra == "dev"
Requires-Dist: pre-commit; extra == "dev"
Requires-Dist: pytest; extra == "dev"
Requires-Dist: pytest-cov; extra == "dev"
Requires-Dist: pytest-env; extra == "dev"
Requires-Dist: pytest-xdist; extra == "dev"
Requires-Dist: ruff; extra == "dev"
Requires-Dist: sphinx; extra == "dev"
Requires-Dist: sphinx-autoapi; extra == "dev"
Requires-Dist: sphinx-book-theme; extra == "dev"
Requires-Dist: sphinx-design; extra == "dev"
Requires-Dist: nbsphinx; extra == "dev"
Requires-Dist: sphinx-tabs; extra == "dev"
Requires-Dist: sphinx-copybutton; extra == "dev"
Requires-Dist: sphinx-togglebutton; extra == "dev"
Requires-Dist: sphinx-rtd-theme; extra == "dev"
Requires-Dist: lsdb; extra == "dev"
Dynamic: license-file
